pulsar/__init__.py
pulsar/logger.py
pulsar/prompt.py
pulsar/promptlib.py
pulsar/client/__init__.py
pulsar/client/anthropic.py
pulsar/client/base.py
pulsar/client/exceptions.py
pulsar/client/gemini.py
pulsar/client/groq.py
pulsar/client/ollama.py
pulsar/client/openai.py
pulsar/client/openaiapilike.py
pulsar/client/openrouter.py
pulsar/client/types.py
pulsar/helpers/__init__.py
pulsar/helpers/func_pydc.py
pulsar/parser/__init__.py
pulsar/parser/json_ast_builder.py
pulsar/parser/json_preprocessor.py
pulsar/parser/json_tokenizer.py
pulsar/parser/json_type_coercer.py
pulsar_struct-0.2.0.dev0.dist-info/LICENSE
pulsar_struct-0.2.0.dev0.dist-info/METADATA
pulsar_struct-0.2.0.dev0.dist-info/WHEEL
pulsar_struct-0.2.0.dev0.dist-info/top_level.txt
pulsar_struct-0.2.0.dev0.dist-info/zip-safe
pulsar_struct-0.2.0.dev0.dist-info/RECORD
