Metadata-Version: 2.2
Name: pulsar-struct
Version: 0.2.0.dev0
Summary: A reliable structured output client.
Author: Rodrigo Baron
License: Apache-2.0
Requires-Python: >=3.10
License-File: LICENSE
Requires-Dist: pydantic
Requires-Dist: pytest
Requires-Dist: requests
Requires-Dist: pre-commit
Requires-Dist: python-dotenv
Requires-Dist: jinja2
